poetry_restrict_plugin/__init__.py
poetry_restrict_plugin/plugin.py
poetry_restrict_plugin-0.1.0a7.dist-info/LICENSE
poetry_restrict_plugin-0.1.0a7.dist-info/METADATA
poetry_restrict_plugin-0.1.0a7.dist-info/WHEEL
poetry_restrict_plugin-0.1.0a7.dist-info/entry_points.txt
poetry_restrict_plugin-0.1.0a7.dist-info/RECORD
