Metadata-Version: 2.1
Name: poetry-restrict-plugin
Version: 0.1.0a7
Summary: Restrict Poetry to a smaller privilege
Home-page: https://git.jchri.st/jc/poetry-restrict-plugin
License: LGPL-3.0-or-later
Keywords: poetry,security,landlock
Author: Johannes Christ
Author-email: jc@jchri.st
Maintainer: Johannes Christ
Maintainer-email: jc@jchri.st
Requires-Python: >=3.11,<4.0
Classifier: Development Status :: 3 - Alpha
Classifier: Intended Audience :: Developers
Classifier: License :: OSI Approved :: GNU Lesser General Public License v3 or later (LGPLv3+)
Classifier: Programming Language :: Python
Classifier: Programming Language :: Python :: 3
Classifier: Programming Language :: Python :: 3.11
Classifier: Programming Language :: Python :: 3.12
Classifier: Topic :: Security
Classifier: Topic :: Software Development :: Build Tools
Requires-Dist: landlock (>=1.0.0.dev4,<2.0.0) ; sys_platform == "linux"
Requires-Dist: poetry (>=1.8.3,<2.0.0)
Project-URL: Repository, https://git.jchri.st/jc/poetry-restrict-plugin
